pgpq-0.9.0.dist-info/METADATA
pgpq-0.9.0.dist-info/WHEEL
pgpq/__init__.py
pgpq/encoders.py
pgpq/py.typed
pgpq/_pgpq.pyi
pgpq/schema.py
pgpq/_pgpq.abi3.so
pgpq-0.9.0.dist-info/RECORD
